symupy/__init__.py
symupy/abstractions/__init__.py
symupy/abstractions/command.py
symupy/abstractions/observer.py
symupy/abstractions/reader.py
symupy/abstractions/subject.py
symupy/cli/__init__.py
symupy/cli/analyze.py
symupy/cli/cli.py
symupy/cli/launch.py
symupy/parser/__init__.py
symupy/parser/csvparser.py
symupy/parser/xmlparser.py
symupy/plugins/__init__.py
symupy/plugins/reader/__init__.py
symupy/plugins/reader/loader.py
symupy/plugins/reader/symuflow.py
symupy/plugins/reader/symumaster.py
symupy/postprocess/__init__.py
symupy/postprocess/analyse.py
symupy/postprocess/visunet/__init__.py
symupy/postprocess/visunet/main.py
symupy/postprocess/visunet/mplfigure.py
symupy/postprocess/visunet/network.py
symupy/postprocess/visunet/qtutils.py
symupy/postprocess/visunet/reader.py
symupy/postprocess/visunet/right_panel.py
symupy/postprocess/visunet/routes.py
symupy/preprocess/__init__.py
symupy/preprocess/analyse.py
symupy/renderer/__init__.py
symupy/renderer/network.py
symupy/renderer/trip.py
symupy/runtime/__init__.py
symupy/runtime/api/__init__.py
symupy/runtime/api/connector.py
symupy/runtime/api/scenario.py
symupy/runtime/api/commands/__init__.py
symupy/runtime/api/commands/nocommand.py
symupy/runtime/logic/__init__.py
symupy/runtime/logic/base.py
symupy/runtime/logic/publisher.py
symupy/runtime/logic/runtime.py
symupy/runtime/logic/sorted_frozen_set.py
symupy/runtime/logic/states.py
symupy/runtime/logic/subscriber.py
symupy/runtime/monitor/__init__.py
symupy/runtime/monitor/manager.py
symupy/runtime/monitor/monitors.py
symupy/tsc/__init__.py
symupy/tsc/dynamics.py
symupy/tsc/journey.py
symupy/tsc/network.py
symupy/tsc/ve2xnetworks.py
symupy/tsc/vehicle_control.py
symupy/tsc/vehicles.py
symupy/utils/__init__.py
symupy/utils/configurator.py
symupy/utils/constants.py
symupy/utils/exceptions.py
symupy/utils/parser.py
symupy/utils/screen.py
symupy/utils/settings.ini
symupy/utils/time.py
symupy/utils/tools.py
symupy/utils/xmlgenerator.py
symupy-1.0.0.dist-info/AUTHORS.md
symupy-1.0.0.dist-info/LICENSE.md
symupy-1.0.0.dist-info/METADATA
symupy-1.0.0.dist-info/WHEEL
symupy-1.0.0.dist-info/entry_points.txt
symupy-1.0.0.dist-info/top_level.txt
symupy-1.0.0.dist-info/RECORD
