Metadata-Version: 2.1
Name: symupy
Version: 1.0.0
Summary: A module for SymuFlow inside Python
Home-page: https://github.com/symuflow/symupy
Author: Andres Ladino
Author-email: aladinoster@gmail.com
Maintainer: Andres Ladino
Maintainer-email: aladinoster@gmail.com
License: MIT
Download-URL: https://github.com/symuflow/symupy
Keywords: traffic microsimulation
Platform: UNKNOWN
Classifier: Development Status :: 2 - Pre-Alpha
Classifier: Intended Audience :: Developers
Classifier: Intended Audience :: Science/Research
Classifier: License :: OSI Approved :: MIT License
Classifier: Topic :: Scientific/Engineering
Classifier: Topic :: Scientific/Engineering :: Mathematics
Classifier: Natural Language :: English
Classifier: Operating System :: Microsoft :: Windows
Classifier: Operating System :: MacOS :: MacOS X
Classifier: Programming Language :: Python :: 3.9
Requires-Python: >=3.7
License-File: LICENSE.md
License-File: AUTHORS.md
Requires-Dist: numpy (>=1.16)
Requires-Dist: lxml (>=4.3.3)
Requires-Dist: networkx (>=2.5)
Requires-Dist: matplotlib (>=3.0.0)
Requires-Dist: sqlalchemy (>=1.3.5)
Requires-Dist: pandas (>=1.0.0)
Requires-Dist: scipy (>=1.4.1)
Requires-Dist: click (>=7.0)
Requires-Dist: python-decouple (>=3.3)
Requires-Dist: PyQt5 (>=5.15.4)
Requires-Dist: pyqtgraph (>=0.12)
